src/lru_controller.v
module lru_controller (
    input wire clk,
    input wire reset,
    input wire [6:0] index,
    input wire [3:0] access_way,
    input wire update_lru,
    output reg [3:0] lru_way
);

    parameter NUM_SETS = 128;

    reg [1:0] lru_counters [3:0] [NUM_SETS-1:0];

    integer i, j;

    initial begin
        for (i = 0; i < 4; i = i + 1) begin
            for (j = 0; j < NUM_SETS; j = j + 1) begin
                lru_counters[i][j] = i[1:0];
            end
        end
    end

    always @(*) begin
        lru_way = 4'b0001;
        
        if ((lru_counters[0][index] >= lru_counters[1][index]) &&
            (lru_counters[0][index] >= lru_counters[2][index]) &&
            (lru_counters[0][index] >= lru_counters[3][index]))
            lru_way = 4'b0001;
        else if ((lru_counters[1][index] >= lru_counters[0][index]) &&
                 (lru_counters[1][index] >= lru_counters[2][index]) &&
                 (lru_counters[1][index] >= lru_counters[3][index]))
            lru_way = 4'b0010;
        else if ((lru_counters[2][index] >= lru_counters[0][index]) &&
                 (lru_counters[2][index] >= lru_counters[1][index]) &&
                 (lru_counters[2][index] >= lru_counters[3][index]))
            lru_way = 4'b0100;
        else
            lru_way = 4'b1000;
    end

    always @(posedge clk) begin
        if (reset) begin
            for (i = 0; i < 4; i = i + 1) begin
                for (j = 0; j < NUM_SETS; j = j + 1) begin
                    lru_counters[i][j] <= i[1:0];
                end
            end
        end else if (update_lru) begin
            for (i = 0; i < 4; i = i + 1) begin
                if (access_way[i]) begin
                    lru_counters[i][index] <= 2'b00;
                end else if (lru_counters[i][index] < 2'b11) begin
                    lru_counters[i][index] <= lru_counters[i][index] + 1;
                end
            end
        end
    end

endmodule

src/data_array.v
module data_array (
    input wire clk,
    input wire reset,
    input wire [6:0] index,
    input wire [511:0] data_in,
    input wire [31:0] word_data_in,
    input wire [3:0] word_offset,
    input wire write_enable,
    input wire word_write_enable,
    input wire [1:0] write_way,
    input wire [3:0] hit_way,
    output wire [511:0] data_out_0,
    output wire [511:0] data_out_1,
    output wire [511:0] data_out_2,
    output wire [511:0] data_out_3
);

    parameter NUM_SETS = 128;
    parameter BLOCK_SIZE = 512;

    reg [BLOCK_SIZE-1:0] data_memory [3:0] [NUM_SETS-1:0];

    integer i, j;

    initial begin
        for (i = 0; i < 4; i = i + 1) begin
            for (j = 0; j < NUM_SETS; j = j + 1) begin
                data_memory[i][j] = 0;
            end
        end
    end

    assign data_out_0 = data_memory[0][index];
    assign data_out_1 = data_memory[1][index];
    assign data_out_2 = data_memory[2][index];
    assign data_out_3 = data_memory[3][index];

    always @(posedge clk) begin
        if (reset) begin
            for (i = 0; i < 4; i = i + 1) begin
                for (j = 0; j < NUM_SETS; j = j + 1) begin
                    data_memory[i][j] <= 0;
                end
            end
        end else if (write_enable) begin
            data_memory[write_way][index] <= data_in;
            $display("DATA_ARRAY: Block write to way %d, index %d, data=%h", 
                     write_way, index, data_in);
        end else if (word_write_enable) begin
            $display("DATA_ARRAY: Word write enable, hit_way=%b, word_offset=%d, data=%h", 
                     hit_way, word_offset, word_data_in);
            if (hit_way[0]) begin
                data_memory[0][index][word_offset*32 +: 32] <= word_data_in;
                $display("DATA_ARRAY: Writing to way 0");
            end
            if (hit_way[1]) begin
                data_memory[1][index][word_offset*32 +: 32] <= word_data_in;
                $display("DATA_ARRAY: Writing to way 1");
            end
            if (hit_way[2]) begin
                data_memory[2][index][word_offset*32 +: 32] <= word_data_in;
                $display("DATA_ARRAY: Writing to way 2");
            end
            if (hit_way[3]) begin
                data_memory[3][index][word_offset*32 +: 32] <= word_data_in;
                $display("DATA_ARRAY: Writing to way 3");
            end
        end
    end

endmodule

src/tag_array.v
module tag_array (
    input wire clk,
    input wire reset,
    input wire [6:0] index,
    input wire [18:0] tag_in,
    input wire write_enable,
    input wire [1:0] write_way,
    output wire [18:0] tag_out_0,
    output wire [18:0] tag_out_1,
    output wire [18:0] tag_out_2,
    output wire [18:0] tag_out_3,
    output wire [3:0] valid_bits
);

    parameter NUM_SETS = 128;
    parameter TAG_BITS = 19;

    reg [TAG_BITS-1:0] tag_memory [3:0] [NUM_SETS-1:0];
    reg valid_memory [3:0] [NUM_SETS-1:0];

    integer i, j;

    initial begin
        for (i = 0; i < 4; i = i + 1) begin
            for (j = 0; j < NUM_SETS; j = j + 1) begin
                tag_memory[i][j] = 0;
                valid_memory[i][j] = 0;
            end
        end
    end

    assign tag_out_0 = tag_memory[0][index];
    assign tag_out_1 = tag_memory[1][index];
    assign tag_out_2 = tag_memory[2][index];
    assign tag_out_3 = tag_memory[3][index];
    
    assign valid_bits[0] = valid_memory[0][index];
    assign valid_bits[1] = valid_memory[1][index];
    assign valid_bits[2] = valid_memory[2][index];
    assign valid_bits[3] = valid_memory[3][index];

    always @(posedge clk) begin
        if (reset) begin
            for (i = 0; i < 4; i = i + 1) begin
                for (j = 0; j < NUM_SETS; j = j + 1) begin
                    tag_memory[i][j] <= 0;
                    valid_memory[i][j] <= 0;
                end
            end
        end else if (write_enable) begin
            tag_memory[write_way][index] <= tag_in;
            valid_memory[write_way][index] <= 1'b1;
        end
    end

endmodule

src/cache_memory.v
module cache_memory (
    input wire clk,
    input wire reset,
    input wire [31:0] address,
    input wire [31:0] write_data,
    input wire [511:0] mem_data_in,
    input wire write_enable,
    input wire mem_write_enable,
    input wire [3:0] lru_way,
    output wire [3:0] hit_way,
    output wire cache_hit,
    output reg [31:0] data_out,
    output reg [511:0] cache_data_out
);

    parameter INDEX_BITS = 7;
    parameter TAG_BITS = 19;
    parameter OFFSET_BITS = 6;
    parameter NUM_SETS = 128;
    parameter ASSOCIATIVITY = 4;

    wire [TAG_BITS-1:0] tag = address[31:13];
    wire [INDEX_BITS-1:0] index = address[12:6];
    wire [OFFSET_BITS-1:0] offset = address[5:0];
    wire [3:0] word_offset = offset[5:2];

    wire [TAG_BITS-1:0] tag_out_0, tag_out_1, tag_out_2, tag_out_3;
    wire [3:0] valid_bits;

    wire [1:0] write_way_select;
    assign write_way_select = (lru_way == 4'b0001) ? 2'b00 :
                             (lru_way == 4'b0010) ? 2'b01 :
                             (lru_way == 4'b0100) ? 2'b10 : 2'b11;

    tag_array tag_array_inst (
        .clk(clk),
        .reset(reset),
        .index(index),
        .tag_in(tag),
        .write_enable(mem_write_enable),
        .write_way(write_way_select),
        .tag_out_0(tag_out_0),
        .tag_out_1(tag_out_1),
        .tag_out_2(tag_out_2),
        .tag_out_3(tag_out_3),
        .valid_bits(valid_bits)
    );

    wire [511:0] data_out_0, data_out_1, data_out_2, data_out_3;

    data_array data_array_inst (
        .clk(clk),
        .reset(reset),
        .index(index),
        .data_in(mem_data_in),
        .word_data_in(write_data),
        .word_offset(word_offset),
        .write_enable(mem_write_enable),
        .word_write_enable(write_enable),
        .write_way(write_way_select),
        .hit_way(hit_way),
        .data_out_0(data_out_0),
        .data_out_1(data_out_1),
        .data_out_2(data_out_2),
        .data_out_3(data_out_3)
    );

    wire [3:0] way_hit;
    assign way_hit[0] = valid_bits[0] && (tag_out_0 == tag);
    assign way_hit[1] = valid_bits[1] && (tag_out_1 == tag);
    assign way_hit[2] = valid_bits[2] && (tag_out_2 == tag);
    assign way_hit[3] = valid_bits[3] && (tag_out_3 == tag);

    assign cache_hit = |way_hit;
    assign hit_way = way_hit;

    always @(*) begin
        data_out = 32'b0;
        cache_data_out = 512'b0;
        
        if (way_hit[0]) begin
            data_out = data_out_0[word_offset*32 +: 32];
            cache_data_out = data_out_0;
        end else if (way_hit[1]) begin
            data_out = data_out_1[word_offset*32 +: 32];
            cache_data_out = data_out_1;
        end else if (way_hit[2]) begin
            data_out = data_out_2[word_offset*32 +: 32];
            cache_data_out = data_out_2;
        end else if (way_hit[3]) begin
            data_out = data_out_3[word_offset*32 +: 32];
            cache_data_out = data_out_3;
        end else begin
            case (lru_way)
                4'b0001: begin
                    data_out = data_out_0[word_offset*32 +: 32];
                    cache_data_out = data_out_0;
                end
                4'b0010: begin
                    data_out = data_out_1[word_offset*32 +: 32];
                    cache_data_out = data_out_1;
                end
                4'b0100: begin
                    data_out = data_out_2[word_offset*32 +: 32];
                    cache_data_out = data_out_2;
                end
                4'b1000: begin
                    data_out = data_out_3[word_offset*32 +: 32];
                    cache_data_out = data_out_3;
                end
                default: begin
                    data_out = data_out_0[word_offset*32 +: 32];
                    cache_data_out = data_out_0;
                end
            endcase
        end
        
        if (|way_hit || |lru_way) begin
            $display("CACHE_MEMORY: way_hit=%b, lru_way=%b, word_offset=%d, data_out=%h", 
                     way_hit, lru_way, word_offset, data_out);
        end
    end

endmodule

src/cache_controller.v
module cache_controller (
    input wire clk,
    input wire reset,
    input wire [31:0] address,
    input wire [31:0] write_data,
    input wire read_enable,
    input wire write_enable,
    output reg [31:0] read_data,
    output reg cache_hit,
    output reg cache_ready,
    output reg [31:0] mem_address,
    output reg [511:0] mem_write_data,
    input wire [511:0] mem_read_data,
    output reg mem_read_enable,
    output reg mem_write_enable,
    input wire mem_ready
);

    parameter CACHE_SIZE = 32768;
    parameter BLOCK_SIZE = 64;
    parameter WORD_SIZE = 4;
    parameter NUM_SETS = 128;
    parameter ASSOCIATIVITY = 4;
    parameter OFFSET_BITS = 6;
    parameter INDEX_BITS = 7;
    parameter TAG_BITS = 19;

    parameter IDLE = 3'b000;
    parameter READ_HIT = 3'b001;
    parameter READ_MISS = 3'b010;
    parameter WRITE_HIT = 3'b011;
    parameter WRITE_MISS = 3'b100;
    parameter EVICT = 3'b101;

    reg [2:0] current_state, next_state;

    wire [TAG_BITS-1:0] tag;
    wire [INDEX_BITS-1:0] index;
    wire [OFFSET_BITS-1:0] offset;
    
    assign tag = address[31:13];
    assign index = address[12:6];
    assign offset = address[5:0];

    wire [3:0] hit_way;
    wire cache_hit_internal;
    wire [511:0] cache_data_out;
    wire [3:0] lru_way;
    wire [31:0] cache_read_data;
    
    wire cache_block_write_enable;
    wire cache_word_write_enable;
    
    assign cache_block_write_enable = (current_state == READ_MISS || current_state == WRITE_MISS) && mem_ready;
    assign cache_word_write_enable = (current_state == WRITE_HIT); 

    reg [31:0] read_data_reg;

    cache_memory cache_mem_inst (
        .clk(clk),
        .reset(reset),
        .address(address),
        .write_data(write_data),
        .mem_data_in(mem_read_data),
        .write_enable(cache_word_write_enable),
        .mem_write_enable(cache_block_write_enable),
        .lru_way(lru_way),
        .hit_way(hit_way),
        .cache_hit(cache_hit_internal),
        .data_out(cache_read_data),
        .cache_data_out(cache_data_out)
    );

    lru_controller lru_inst (
        .clk(clk),
        .reset(reset),
        .index(index),
        .access_way(hit_way),
        .update_lru(cache_hit_internal && (current_state == READ_HIT || current_state == WRITE_HIT)),
        .lru_way(lru_way)
    );

    always @(posedge clk or posedge reset) begin
        if (reset) begin
            current_state <= IDLE;
            read_data_reg <= 32'b0;
        end else begin
            current_state <= next_state;
            
            if (current_state == READ_HIT) begin
                read_data_reg <= cache_read_data;
            end
            
            if (current_state == READ_MISS && next_state == IDLE) begin
                read_data_reg <= cache_read_data;
            end
        end
    end

    always @(*) begin
        next_state = current_state;
        case (current_state)
            IDLE: begin
                if (read_enable && cache_hit_internal) 
                    next_state = READ_HIT;
                else if (read_enable && !cache_hit_internal)
                    next_state = READ_MISS;
                else if (write_enable && cache_hit_internal)
                    next_state = WRITE_HIT;
                else if (write_enable && !cache_hit_internal)
                    next_state = WRITE_MISS;
            end
            
            READ_HIT: next_state = IDLE;
            
            READ_MISS: begin
                if (mem_ready)
                    next_state = IDLE;
            end
            
            WRITE_HIT: next_state = IDLE;
            
            WRITE_MISS: begin
                if (mem_ready)
                    next_state = IDLE;
            end
            
            EVICT: begin
                if (mem_ready)
                    next_state = WRITE_MISS;
            end
        endcase
    end

    always @(*) begin
        cache_hit = 1'b0;
        cache_ready = 1'b0;
        mem_address = 32'b0;
        mem_write_data = 512'b0;
        mem_read_enable = 1'b0;
        mem_write_enable = 1'b0;
        read_data = read_data_reg;

        case (current_state)
            IDLE: begin
                cache_ready = 1'b1;
                if (cache_hit_internal) begin
                    read_data = cache_read_data;
                end
            end
            
            READ_HIT: begin
                cache_hit = 1'b1;
                cache_ready = 1'b1;
                read_data = cache_read_data; 
            end
            
            READ_MISS: begin
                mem_address = {address[31:6], 6'b0};
                mem_read_enable = 1'b1;
                cache_ready = mem_ready;
                if (mem_ready) begin
                    read_data = cache_read_data;
                end
            end
            
            WRITE_HIT: begin
                cache_hit = 1'b1;
                cache_ready = 1'b1;
            end
            
            WRITE_MISS: begin
                mem_address = {address[31:6], 6'b0};
                mem_read_enable = 1'b1;
                cache_ready = mem_ready;
            end
            
            EVICT: begin
                mem_address = {address[31:6], 6'b0};
                mem_write_data = cache_data_out;
                mem_write_enable = 1'b1;
            end
        endcase
    end

endmodule

testbench/cache_controller_tb.v
module cache_controller_tb;

    parameter ADDR_WIDTH = 32;
    parameter DATA_WIDTH = 32;
    parameter CACHE_SIZE = 32 * 1024; // 32 KB
    parameter BLOCK_SIZE = 64; // 64 bytes
    parameter NUM_SETS = 128; // 128 sets
    parameter ASSOC = 4; // 4-way set associative

    reg clk;
    reg reset;

    reg [31:0] address;
    reg [31:0] write_data;
    reg read_enable;
    reg write_enable;
    wire [31:0] read_data;
    wire cache_hit;
    wire cache_ready;

    wire [31:0] mem_address;
    wire [511:0] mem_write_data;
    reg [511:0] mem_read_data;
    wire mem_read_enable;
    wire mem_write_enable;
    reg mem_ready;

    cache_controller uut (
        .clk(clk),
        .reset(reset),
        .address(address),
        .write_data(write_data),
        .read_enable(read_enable),
        .write_enable(write_enable),
        .read_data(read_data),
        .cache_hit(cache_hit),
        .cache_ready(cache_ready),
        .mem_address(mem_address),
        .mem_write_data(mem_write_data),
        .mem_read_data(mem_read_data),
        .mem_read_enable(mem_read_enable),
        .mem_write_enable(mem_write_enable),
        .mem_ready(mem_ready)
    );

    initial begin
        clk = 0;
        forever #5 clk = ~clk;
    end

    initial begin
        reset = 1;
        address = 0;
        write_data = 0;
        read_enable = 0;
        write_enable = 0;
        mem_read_data = 0;
        mem_ready = 1;

        #20 reset = 0;
        #10;

        $display("=== Cache Controller Testbench ===");
        $display("Time=%0t: Starting cache controller tests", $time);

        $display("\n=== Test 1: Read miss from empty cache ===");
        address = 32'h00001000;
        mem_read_data = {16{32'hDEADBEEF}};

        $display("Before READ_MISS: Setting mem_read_data to first 32 bits: %h", mem_read_data[31:0]);
        
        read_enable = 1;
        @(posedge clk);
        
        while (!cache_ready) @(posedge clk);
        
        read_enable = 0;
        @(posedge clk);
        @(posedge clk);
        @(posedge clk); //Waiting for the waiter to wait
        
        $display("After READ_MISS: read_data=%h", read_data);
        $display("cache_hit_internal=%b, cache_block_write_enable=%b", 
                 uut.cache_hit_internal, uut.cache_block_write_enable);
        $display("cache_read_data=%h", uut.cache_read_data);
        $display("Expected: DEADBEEF, Got: %h %s", read_data, 
                 (read_data == 32'hDEADBEEF) ? "PASS" : "FAIL");

        $display("\n=== Test 2: Read hit (same address) ===");
        address = 32'h00001000;
        
        read_enable = 1;
        @(posedge clk);
        
        while (!cache_ready) @(posedge clk);
        
        read_enable = 0;
        @(posedge clk);
        
        $display("After READ_HIT: read_data=%h, cache_hit=%b", read_data, cache_hit);
        $display("cache_read_data=%h", uut.cache_read_data);
        $display("Expected: DEADBEEF, Got: %h %s", read_data,
                 (read_data == 32'hDEADBEEF) ? "PASS" : "FAIL");

        $display("\n=== Test 3: Write hit with NEW data ===");
        address = 32'h00001000;
        write_data = 32'hAAAABBBB;
        
        $display("Writing %h to address %h", write_data, address);
        $display("Before write: cache_word_write_enable=%b", uut.cache_word_write_enable);
        
        write_enable = 1;
        @(posedge clk);
        
        $display("During write: current_state=%d, cache_word_write_enable=%b", 
                 uut.current_state, uut.cache_word_write_enable);
        
        while (!cache_ready) @(posedge clk);
        
        write_enable = 0;
        @(posedge clk);
        @(posedge clk);
        
        $display("After WRITE_HIT: cache_hit=%b", cache_hit);

        $display("\n=== Test 4: Read back written data ===");
        address = 32'h00001000;
        
        read_enable = 1;
        @(posedge clk);
        
        while (!cache_ready) @(posedge clk);
        
        read_enable = 0;
        @(posedge clk);
        
        $display("After reading written data: read_data=%h, cache_hit=%b", read_data, cache_hit);
        $display("cache_read_data=%h", uut.cache_read_data);
        $display("Expected: AAAABBBB, Got: %h %s", read_data,
                 (read_data == 32'hAAAABBBB) ? "PASS" : "FAIL");

        $display("\n=== Test 5: Read miss from different address ===");
        address = 32'h00002000;
        mem_read_data = {16{32'h12345678}};
        
        $display("Setting mem_read_data to first 32 bits: %h for address %h", mem_read_data[31:0], address);
        
        read_enable = 1;
        @(posedge clk);
        
        while (!cache_ready) @(posedge clk);
        
        read_enable = 0;
        @(posedge clk);
        @(posedge clk);
        
        $display("After READ_MISS: read_data=%h", read_data);
        $display("cache_read_data=%h", uut.cache_read_data);
        $display("Expected: 12345678, Got: %h %s", read_data,
                 (read_data == 32'h12345678) ? "PASS" : "FAIL");

        $display("\n=== Test 6: Write to second address ===");
        address = 32'h00002000;
        write_data = 32'hCCCCDDDD;
        
        write_enable = 1;
        @(posedge clk);
        
        while (!cache_ready) @(posedge clk);
        
        write_enable = 0;
        @(posedge clk);
        @(posedge clk);

        read_enable = 1;
        @(posedge clk);
        
        while (!cache_ready) @(posedge clk);
        
        read_enable = 0;
        @(posedge clk);
        
        $display("After writing and reading back: read_data=%h", read_data);
        $display("Expected: CCCCDDDD, Got: %h %s", read_data,
                 (read_data == 32'hCCCCDDDD) ? "PASS" : "FAIL");

        $display("\n=== Test 7: Verify first address data persistence ===");
        address = 32'h00001000;
        
        read_enable = 1;
        @(posedge clk);
        
        while (!cache_ready) @(posedge clk);
        
        read_enable = 0;
        @(posedge clk);
        
        $display("Reading first address again: read_data=%h", read_data);
        $display("Expected: AAAABBBB, Got: %h %s", read_data,
                 (read_data == 32'hAAAABBBB) ? "PASS" : "FAIL");

        $display("\n=== Summary ===");
        $display("Cache controller comprehensive test completed");
        
        #50;
        $finish;
    end

    always @(posedge clk) begin
        if (uut.current_state != uut.next_state || read_enable || write_enable) begin
            $display("Clock: State=%0d->%0d, Addr=%h, R=%b, W=%b, Hit_int=%b, Hit=%b, Data=%h", 
                     uut.current_state, uut.next_state, address, read_enable, write_enable, 
                     uut.cache_hit_internal, cache_hit, read_data);
            $display("       cache_read_data=%h, block_we=%b, word_we=%b", 
                     uut.cache_read_data, uut.cache_block_write_enable, uut.cache_word_write_enable);
        end
    end

    initial begin
        $dumpfile("cache_controller.vcd");
        $dumpvars(0, cache_controller_tb);
    end

endmodule

cache_controller.vcd
$date
	Sat Jun  7 01:20:50 2025
$end
$version
	Icarus Verilog
$end
$timescale
	1s
$end
$scope module cache_controller_tb $end
$var wire 32 ! read_data [31:0] $end
$var wire 1 " mem_write_enable $end
$var wire 512 # mem_write_data [511:0] $end
$var wire 1 $ mem_read_enable $end
$var wire 32 % mem_address [31:0] $end
$var wire 1 & cache_ready $end
$var wire 1 ' cache_hit $end
$var parameter 32 ( ADDR_WIDTH $end
$var parameter 32 ) ASSOC $end
$var parameter 32 * BLOCK_SIZE $end
$var parameter 64 + CACHE_SIZE $end
$var parameter 32 , DATA_WIDTH $end
$var parameter 32 - NUM_SETS $end
$var reg 32 . address [31:0] $end
$var reg 1 / clk $end
$var reg 512 0 mem_read_data [511:0] $end
$var reg 1 1 mem_ready $end
$var reg 1 2 read_enable $end
$var reg 1 3 reset $end
$var reg 32 4 write_data [31:0] $end
$var reg 1 5 write_enable $end
$scope module uut $end
$var wire 32 6 address [31:0] $end
$var wire 1 7 cache_block_write_enable $end
$var wire 1 / clk $end
$var wire 512 8 mem_read_data [511:0] $end
$var wire 1 1 mem_ready $end
$var wire 1 2 read_enable $end
$var wire 1 3 reset $end
$var wire 32 9 write_data [31:0] $end
$var wire 1 5 write_enable $end
$var wire 19 : tag [18:0] $end
$var wire 6 ; offset [5:0] $end
$var wire 4 < lru_way [3:0] $end
$var wire 7 = index [6:0] $end
$var wire 4 > hit_way [3:0] $end
$var wire 1 ? cache_word_write_enable $end
$var wire 32 @ cache_read_data [31:0] $end
$var wire 1 A cache_hit_internal $end
$var wire 512 B cache_data_out [511:0] $end
$var parameter 32 C ASSOCIATIVITY $end
$var parameter 32 D BLOCK_SIZE $end
$var parameter 32 E CACHE_SIZE $end
$var parameter 3 F EVICT $end
$var parameter 3 G IDLE $end
$var parameter 32 H INDEX_BITS $end
$var parameter 32 I NUM_SETS $end
$var parameter 32 J OFFSET_BITS $end
$var parameter 3 K READ_HIT $end
$var parameter 3 L READ_MISS $end
$var parameter 32 M TAG_BITS $end
$var parameter 32 N WORD_SIZE $end
$var parameter 3 O WRITE_HIT $end
$var parameter 3 P WRITE_MISS $end
$var reg 1 ' cache_hit $end
$var reg 1 & cache_ready $end
$var reg 3 Q current_state [2:0] $end
$var reg 32 R mem_address [31:0] $end
$var reg 1 $ mem_read_enable $end
$var reg 512 S mem_write_data [511:0] $end
$var reg 1 " mem_write_enable $end
$var reg 3 T next_state [2:0] $end
$var reg 32 U read_data [31:0] $end
$var reg 32 V read_data_reg [31:0] $end
$scope module cache_mem_inst $end
$var wire 32 W address [31:0] $end
$var wire 1 / clk $end
$var wire 4 X hit_way [3:0] $end
$var wire 512 Y mem_data_in [511:0] $end
$var wire 1 7 mem_write_enable $end
$var wire 1 3 reset $end
$var wire 32 Z write_data [31:0] $end
$var wire 1 ? write_enable $end
$var wire 2 [ write_way_select [1:0] $end
$var wire 4 \ word_offset [3:0] $end
$var wire 4 ] way_hit [3:0] $end
$var wire 4 ^ valid_bits [3:0] $end
$var wire 19 _ tag_out_3 [18:0] $end
$var wire 19 ` tag_out_2 [18:0] $end
$var wire 19 a tag_out_1 [18:0] $end
$var wire 19 b tag_out_0 [18:0] $end
$var wire 19 c tag [18:0] $end
$var wire 6 d offset [5:0] $end
$var wire 4 e lru_way [3:0] $end
$var wire 7 f index [6:0] $end
$var wire 512 g data_out_3 [511:0] $end
$var wire 512 h data_out_2 [511:0] $end
$var wire 512 i data_out_1 [511:0] $end
$var wire 512 j data_out_0 [511:0] $end
$var wire 1 A cache_hit $end
$var parameter 32 k ASSOCIATIVITY $end
$var parameter 32 l INDEX_BITS $end
$var parameter 32 m NUM_SETS $end
$var parameter 32 n OFFSET_BITS $end
$var parameter 32 o TAG_BITS $end
$var reg 512 p cache_data_out [511:0] $end
$var reg 32 q data_out [31:0] $end
$scope module data_array_inst $end
$var wire 1 / clk $end
$var wire 512 r data_in [511:0] $end
$var wire 512 s data_out_0 [511:0] $end
$var wire 512 t data_out_1 [511:0] $end
$var wire 512 u data_out_2 [511:0] $end
$var wire 512 v data_out_3 [511:0] $end
$var wire 4 w hit_way [3:0] $end
$var wire 7 x index [6:0] $end
$var wire 1 3 reset $end
$var wire 32 y word_data_in [31:0] $end
$var wire 4 z word_offset [3:0] $end
$var wire 1 ? word_write_enable $end
$var wire 1 7 write_enable $end
$var wire 2 { write_way [1:0] $end
$var parameter 32 | BLOCK_SIZE $end
$var parameter 32 } NUM_SETS $end
$var integer 32 ~ i [31:0] $end
$var integer 32 !" j [31:0] $end
$upscope $end
$scope module tag_array_inst $end
$var wire 1 / clk $end
$var wire 7 "" index [6:0] $end
$var wire 1 3 reset $end
$var wire 19 #" tag_in [18:0] $end
$var wire 19 $" tag_out_0 [18:0] $end
$var wire 19 %" tag_out_1 [18:0] $end
$var wire 19 &" tag_out_2 [18:0] $end
$var wire 19 '" tag_out_3 [18:0] $end
$var wire 1 7 write_enable $end
$var wire 2 (" write_way [1:0] $end
$var wire 4 )" valid_bits [3:0] $end
$var parameter 32 *" NUM_SETS $end
$var parameter 32 +" TAG_BITS $end
$var integer 32 ," i [31:0] $end
$var integer 32 -" j [31:0] $end
$upscope $end
$upscope $end
$scope module lru_inst $end
$var wire 4 ." access_way [3:0] $end
$var wire 1 / clk $end
$var wire 7 /" index [6:0] $end
$var wire 1 3 reset $end
$var wire 1 0" update_lru $end
$var parameter 32 1" NUM_SETS $end
$var reg 4 2" lru_way [3:0] $end
$var integer 32 3" i [31:0] $end
$var integer 32 4" j [31:0] $end
$upscope $end
$upscope $end
$upscope $end
$enddefinitions $end
$comment Show the parameter values. $end
$dumpall
b10000000 1"
b10011 +"
b10000000 *"
b10000000 }
b1000000000 |
b10011 o
b110 n
b10000000 m
b111 l
b100 k
b100 P
b11 O
b100 N
b10011 M
b10 L
b1 K
b110 J
b10000000 I
b111 H
b0 G
b101 F
b1000000000000000 E
b1000000 D
b100 C
b10000000 -
b100000 ,
b1000000000000000 +
b1000000 *
b100 )
b100000 (
$end
#0
$dumpvars
b10000000 4"
b100 3"
b1000 2"
00"
b0 /"
b0 ."
b10000000 -"
b100 ,"
b0 )"
b11 ("
b0 '"
b0 &"
b0 %"
b0 $"
b0 #"
b0 ""
b10000000 !"
b100 ~
b11 {
b0 z
b0 y
b0 x
b0 w
b0 v
b0 u
b0 t
b0 s
b0 r
b0 q
b0 p
b0 j
b0 i
b0 h
b0 g
b0 f
b1000 e
b0 d
b0 c
b0 b
b0 a
b0 `
b0 _
b0 ^
b0 ]
b0 \
b11 [
b0 Z
b0 Y
b0 X
b0 W
b0 V
b0 U
b0 T
b0 S
b0 R
b0 Q
b0 B
0A
b0 @
0?
b0 >
b0 =
b1000 <
b0 ;
b0 :
b0 9
b0 8
07
b0 6
05
b0 4
13
02
11
b0 0
0/
b0 .
0'
1&
b0 %
0$
b0 #
0"
b0 !
$end
#5
b10000000 -"
b100 ,"
b10000000 !"
b100 ~
b10000000 4"
b100 3"
1/
#10
0/
#15
b10000000 4"
b100 3"
b10000000 !"
b100 ~
b10000000 -"
b100 ,"
1/
#20
0/
03
#25
1/
#30
b1000 <
b1000 e
b1000 2"
b10 T
b1000000 =
b1000000 /"
b1000000 f
b1000000 x
b1000000 ""
1&
0/
12
b11011110101011011011111011101111110111101010110110111110111011111101111010101101101111101110111111011110101011011011111011101111110111101010110110111110111011111101111010101101101111101110111111011110101011011011111011101111110111101010110110111110111011111101111010101101101111101110111111011110101011011011111011101111110111101010110110111110111011111101111010101101101111101110111111011110101011011011111011101111110111101010110110111110111011111101111010101101101111101110111111011110101011011011111011101111 0
b11011110101011011011111011101111110111101010110110111110111011111101111010101101101111101110111111011110101011011011111011101111110111101010110110111110111011111101111010101101101111101110111111011110101011011011111011101111110111101010110110111110111011111101111010101101101111101110111111011110101011011011111011101111110111101010110110111110111011111101111010101101101111101110111111011110101011011011111011101111110111101010110110111110111011111101111010101101101111101110111111011110101011011011111011101111 8
b11011110101011011011111011101111110111101010110110111110111011111101111010101101101111101110111111011110101011011011111011101111110111101010110110111110111011111101111010101101101111101110111111011110101011011011111011101111110111101010110110111110111011111101111010101101101111101110111111011110101011011011111011101111110111101010110110111110111011111101111010101101101111101110111111011110101011011011111011101111110111101010110110111110111011111101111010101101101111101110111111011110101011011011111011101111 Y
b11011110101011011011111011101111110111101010110110111110111011111101111010101101101111101110111111011110101011011011111011101111110111101010110110111110111011111101111010101101101111101110111111011110101011011011111011101111110111101010110110111110111011111101111010101101101111101110111111011110101011011011111011101111110111101010110110111110111011111101111010101101101111101110111111011110101011011011111011101111110111101010110110111110111011111101111010101101101111101110111111011110101011011011111011101111 r
b1000000000000 .
b1000000000000 6
b1000000000000 W
#35
17
1$
b1000000000000 %
b1000000000000 R
1&
b10 Q
b0 T
02
1/
#40
0/
#45
b11011110101011011011111011101111 !
b11011110101011011011111011101111 U
1A
b1000 >
b1000 X
b1000 w
b1000 ."
b1000 ]
07
b11011110101011011011111011101111110111101010110110111110111011111101111010101101101111101110111111011110101011011011111011101111110111101010110110111110111011111101111010101101101111101110111111011110101011011011111011101111110111101010110110111110111011111101111010101101101111101110111111011110101011011011111011101111110111101010110110111110111011111101111010101101101111101110111111011110101011011011111011101111110111101010110110111110111011111101111010101101101111101110111111011110101011011011111011101111 B
b11011110101011011011111011101111110111101010110110111110111011111101111010101101101111101110111111011110101011011011111011101111110111101010110110111110111011111101111010101101101111101110111111011110101011011011111011101111110111101010110110111110111011111101111010101101101111101110111111011110101011011011111011101111110111101010110110111110111011111101111010101101101111101110111111011110101011011011111011101111110111101010110110111110111011111101111010101101101111101110111111011110101011011011111011101111 p
b11011110101011011011111011101111 @
b11011110101011011011111011101111 q
0$
b0 %
b0 R
1&
b1000 ^
b1000 )"
b11011110101011011011111011101111110111101010110110111110111011111101111010101101101111101110111111011110101011011011111011101111110111101010110110111110111011111101111010101101101111101110111111011110101011011011111011101111110111101010110110111110111011111101111010101101101111101110111111011110101011011011111011101111110111101010110110111110111011111101111010101101101111101110111111011110101011011011111011101111110111101010110110111110111011111101111010101101101111101110111111011110101011011011111011101111 g
b11011110101011011011111011101111110111101010110110111110111011111101111010101101101111101110111111011110101011011011111011101111110111101010110110111110111011111101111010101101101111101110111111011110101011011011111011101111110111101010110110111110111011111101111010101101101111101110111111011110101011011011111011101111110111101010110110111110111011111101111010101101101111101110111111011110101011011011111011101111110111101010110110111110111011111101111010101101101111101110111111011110101011011011111011101111 v
b0 Q
1/
#50
0/
#55
1/
#60
0/
#65
b1 T
12
1/
#70
0/
#75
10"
1'
b11011110101011011011111011101111 !
b11011110101011011011111011101111 U
1&
b1 Q
b0 T
02
1/
#80
0/
